ntscli_cloud_lib/__init__.py
ntscli_cloud_lib/__version__.py
ntscli_cloud_lib/automator.py
ntscli_cloud_lib/automator_help.py
ntscli_cloud_lib/device_identifier.py
ntscli_cloud_lib/log.py
ntscli_cloud_lib/mqtt_retryable_error.py
ntscli_cloud_lib/retry_with_backoff.py
ntscli_cloud_lib/self_responder.py
ntscli_cloud_lib/session.py
ntscli_cloud_lib/sslconfig.py
ntscli_cloud_lib/sslconfigmanager.py
ntscli_cloud_lib/stateful_session.py
ntscli_cloud_lib/status_watcher_interface.py
ntscli_cloud_lib/testplan_checker.py
ntscli_cloud_lib-1.1.0.dist-info/METADATA
ntscli_cloud_lib-1.1.0.dist-info/WHEEL
ntscli_cloud_lib-1.1.0.dist-info/dependency_links.txt
ntscli_cloud_lib-1.1.0.dist-info/top_level.txt
ntscli_cloud_lib-1.1.0.dist-info/RECORD
