Metadata-Version: 2.1
Name: ntscli-cloud-lib
Version: 1.1.0
Summary: ntscli-cloud-lib
Home-page: https://stash.corp.netflix.com/projects/~DAVIDB/repos/ntscli_cloud_lib/browse
Author: TSC
Author-email: tsc-team@netflix.com
Keywords: ntscli_cloud_lib
Requires-Python: >=3.6
Requires-Dist: arrow
Requires-Dist: betterproto
Requires-Dist: kaiju-mqtt-py (>=3.0.0)
Requires-Dist: requests
Requires-Dist: dataclasses ; python_version < "3.7"
Provides-Extra: dev
Requires-Dist: behave ; extra == 'dev'
Requires-Dist: betterproto[compiler] ; extra == 'dev'
Requires-Dist: flake8 ; extra == 'dev'
Requires-Dist: invoke ; extra == 'dev'
Requires-Dist: mypy ; extra == 'dev'
Requires-Dist: pytest ; extra == 'dev'
Requires-Dist: tox ; extra == 'dev'
Requires-Dist: twine ; extra == 'dev'
Provides-Extra: test
Requires-Dist: tox ; extra == 'test'
